<?xml version="1.0" encoding="UTF-8"?>
<UnityGameFramework>
  <AssetBundleBuilder>
    <Settings>
      <InternalResourceVersion>0</InternalResourceVersion>
      <Platforms>192</Platforms>
      <ZipSelected>True</ZipSelected>
      <UncompressedAssetBundleSelected>False</UncompressedAssetBundleSelected>
      <DisableWriteTypeTreeSelected>False</DisableWriteTypeTreeSelected>
      <DeterministicAssetBundleSelected>True</DeterministicAssetBundleSelected>
      <ForceRebuildAssetBundleSelected>False</ForceRebuildAssetBundleSelected>
      <IgnoreTypeTreeChangesSelected>False</IgnoreTypeTreeChangesSelected>
      <AppendHashToAssetBundleNameSelected>False</AppendHashToAssetBundleNameSelected>
      <ChunkBasedCompressionSelected>True</ChunkBasedCompressionSelected>
      <OutputPackageSelected>True</OutputPackageSelected>
      <OutputFullSelected>True</OutputFullSelected>
      <OutputPackedSelected>True</OutputPackedSelected>
      <BuildEventHandlerTypeName>
      </BuildEventHandlerTypeName>
      <OutputDirectory>E:/游戏开发小岛/Release</OutputDirectory>
    </Settings>
  </AssetBundleBuilder>
</UnityGameFramework>